snippetcompiler/__init__.py
snippetcompiler/cli.py
snippet_compiler-0.0.6.dist-info/METADATA
snippet_compiler-0.0.6.dist-info/WHEEL
snippet_compiler-0.0.6.dist-info/entry_points.txt
snippet_compiler-0.0.6.dist-info/RECORD
